china_union_lotto/__init__.py
china_union_lotto/server.py
china_union_lotto-0.1.1.dist-info/METADATA
china_union_lotto-0.1.1.dist-info/WHEEL
china_union_lotto-0.1.1.dist-info/entry_points.txt
china_union_lotto-0.1.1.dist-info/top_level.txt
china_union_lotto-0.1.1.dist-info/RECORD
