Metadata-Version: 2.4
Name: china-union-lotto
Version: 0.1.1
Summary: China Union Lotto MCP Server
Requires-Python: >=3.12
Requires-Dist: fastmcp>=2.12.5
Requires-Dist: mcp>=1.0.0
